necromancy/VERSION
necromancy/__init__.py
necromancy/main.py
necromancy-0.0.0.dist-info/LICENSE
necromancy-0.0.0.dist-info/METADATA
necromancy-0.0.0.dist-info/WHEEL
necromancy-0.0.0.dist-info/top_level.txt
necromancy-0.0.0.dist-info/RECORD
