Metadata-Version: 2.1
Name: necromancy
Version: 0.0.0
Summary: Our organization's package
Author-email: Apostolos Filippas <apostolos@goemeritus.com>
License: private
License-File: LICENSE
